MANIFEST.in
README.md
requirements.txt
setup.cfg
setup.py
pinnacle/__init__.py
pinnacle/apiclient.py
pinnacle/baseclient.py
pinnacle/compat.py
pinnacle/enums.py
pinnacle/exceptions.py
pinnacle/utils.py
pinnacle/endpoints/__init__.py
pinnacle/endpoints/account.py
pinnacle/endpoints/baseendpoint.py
pinnacle/endpoints/betting.py
pinnacle/endpoints/marketdata.py
pinnacle/endpoints/referencedata.py
pinnacle/resources/__init__.py
pinnacle/resources/accountresources.py
pinnacle/resources/baseresource.py
pinnacle/resources/bettingresources.py
pinnacle/resources/marketdataresources.py
pinnacle/resources/referencedataresources.py
pinnacle/tests/__init__.py
pinnacle/tests/test_account.py
pinnacle/tests/test_apiclient.py
pinnacle/tests/test_baseclient.py
pinnacle/tests/test_betting.py
pinnacle/tests/test_marketdata.py
pinnacle/tests/test_referencedata.py
pinnacle/tests/test_utils.py
pinnacle_nick.egg-info/PKG-INFO
pinnacle_nick.egg-info/SOURCES.txt
pinnacle_nick.egg-info/dependency_links.txt
pinnacle_nick.egg-info/requires.txt
pinnacle_nick.egg-info/top_level.txt