Metadata-Version: 1.0
Name: pinnacle-nick
Version: 0.0.7
Summary: Pinnacle Nick API Python wrapper
Home-page: https://github.com/rozzac90/pinnacle
Author: Nick Georgiadis
Author-email: nickgeo_@hotmail.com
License: UNKNOWN
Platform: UNKNOWN
